pyscrings-0.1.6.dist-info/METADATA
pyscrings-0.1.6.dist-info/WHEEL
pyscrings/__init__.py
pyscrings/pyscrings.abi3.so
pyscrings-0.1.6.dist-info/RECORD
