Metadata-Version: 2.4
Name: pyscrings
Version: 0.1.6
Classifier: Programming Language :: Rust
Classifier: Programming Language :: Python :: Implementation :: CPython
Classifier: Programming Language :: Python :: Implementation :: PyPy
Summary: Semantic strings based on tree-sitter
Requires-Python: >=3.8
